rowantree/auth/sdk/__init__.py
rowantree/auth/sdk/commands/__init__.py
rowantree/auth/sdk/commands/abstract_command.py
rowantree/auth/sdk/commands/authenticate_user.py
rowantree/auth/sdk/commands/register_user.py
rowantree/auth/sdk/common/__init__.py
rowantree/auth/sdk/common/claims.py
rowantree/auth/sdk/common/depends.py
rowantree/auth/sdk/common/jwt.py
rowantree/auth/sdk/common/password.py
rowantree/auth/sdk/contracts/__init__.py
rowantree/auth/sdk/contracts/exceeded_retry_count_error.py
rowantree/auth/sdk/contracts/request_failure_error.py
rowantree/auth/sdk/contracts/request_verb.py
rowantree/auth/sdk/contracts/dto/__init__.py
rowantree/auth/sdk/contracts/dto/command_options.py
rowantree/auth/sdk/contracts/dto/request_status_codes.py
rowantree/auth/sdk/contracts/dto/token.py
rowantree/auth/sdk/contracts/dto/token_claims.py
rowantree/auth/sdk/contracts/dto/wrapped_request.py
rowantree/auth/sdk/contracts/dto/user/__init__.py
rowantree/auth/sdk/contracts/dto/user/base.py
rowantree/auth/sdk/contracts/dto/user/user.py
rowantree/auth/sdk/contracts/requests/__init__.py
rowantree/auth/sdk/contracts/requests/authenticate_user_request.py
rowantree/auth/sdk/contracts/requests/register_user_request.py
rowantree.auth.sdk-0.20.0.dist-info/LICENSE
rowantree.auth.sdk-0.20.0.dist-info/METADATA
rowantree.auth.sdk-0.20.0.dist-info/WHEEL
rowantree.auth.sdk-0.20.0.dist-info/top_level.txt
rowantree.auth.sdk-0.20.0.dist-info/RECORD
