Metadata-Version: 2.1
Name: rowantree.auth.sdk
Version: 0.20.0
Summary: The Rowan Tree Authentication and Authorization Service SDK
Author: Joshua C. Burt
Author-email: joshburt@shapeandshare.com
License: MIT
Requires-Python: >=3.9
License-File: LICENSE
Requires-Dist: pydantic (~=1.10)
Requires-Dist: requests (~=2.28)
Requires-Dist: python-jose (~=3.3)
Requires-Dist: fastapi (~=0.81)
Requires-Dist: starlette (~=0.19)
Requires-Dist: bcrypt (~=4.0)
Requires-Dist: passlib (~=1.7)
Requires-Dist: rowantree.common.sdk (~=0.4)
Requires-Dist: rowantree.contracts (~=0.16)
